expbox/__init__.py
expbox/api.py
expbox/cli.py
expbox/core.py
expbox/exceptions.py
expbox/ids.py
expbox/io.py
expbox/logger.py
expbox-0.4.1.dist-info/licenses/LICENSE
expbox-0.4.1.dist-info/METADATA
expbox-0.4.1.dist-info/WHEEL
expbox-0.4.1.dist-info/entry_points.txt
expbox-0.4.1.dist-info/top_level.txt
expbox-0.4.1.dist-info/RECORD
