Metadata-Version: 2.4
Name: expbox
Version: 0.4.1
Summary: A lightweight experiment context & result management helper.
Author-email: Tadahaya Mizuno <tadahaya@gmail.com>
Project-URL: Homepage, https://github.com/mizuno-group/expbox
Requires-Python: >=3.9
License-File: LICENSE
Provides-Extra: wandb
Requires-Dist: wandb>=0.16.0; extra == "wandb"
Provides-Extra: yaml
Requires-Dist: pyyaml>=6.0; extra == "yaml"
Provides-Extra: dev
Requires-Dist: pytest>=8.0; extra == "dev"
Requires-Dist: pytest-cov; extra == "dev"
Dynamic: license-file
